{"3146": {"GOLD": 0, "deaths": 0, "TOP": 0, "magicDamageDealtToChampions": 0, "CHALLENGER": 0, "totalTimeCrowdControlDealt": 0, "PLATINUM": 0, "NONE": 0, "BOTTOM": 0, "winner": 0, "spell1": 0, "MASTER": 0, "JUNGLE": 0, "UNRANKED": 0, "DUO_CARRY": 0, "spell21": 0, "SOLO": 0, "magicDamageDealt": 0, "kills": 0, "DUO": 0, "timestamp": 0, "MIDDLE": 0, "assists": 0, "spell4": 0, "spell6": 0, "spell7": 0, "SILVER": 0, "BRONZE": 0, "spell3": 0, "count": 0, "spell14": 0, "DIAMOND": 0, "spell12": 0, "spell13": 0, "spell11": 0, "pickRate": 0.0, "spell2": 0, "DUO_SUPPORT": 0}, "3023": {"GOLD": 0, "deaths": 0, "TOP": 0, "magicDamageDealtToChampions": 0, "CHALLENGER": 0, "totalTimeCrowdControlDealt": 0, "PLATINUM": 0, "NONE": 0, "BOTTOM": 0, "winner": 0, "spell1": 0, "MASTER": 0, "JUNGLE": 0, "UNRANKED": 0, "DUO_CARRY": 0, "spell21": 0, "SOLO": 0, "magicDamageDealt": 0, "kills": 0, "DUO": 0, "timestamp": 0, "MIDDLE": 0, "assists": 0, "spell4": 0, "spell6": 0, "spell7": 0, "SILVER": 0, "BRONZE": 0, "spell3": 0, "count": 0, "spell14": 0, "DIAMOND": 0, "spell12": 0, "spell13": 0, "spell11": 0, "pickRate": 0.0, "spell2": 0, "DUO_SUPPORT": 0}, "3060": {"GOLD": 0, "deaths": 0, "TOP": 0, "magicDamageDealtToChampions": 0, "CHALLENGER": 0, "totalTimeCrowdControlDealt": 0, "PLATINUM": 0, "NONE": 0, "BOTTOM": 0, "winner": 0, "spell1": 0, "MASTER": 0, "JUNGLE": 0, "UNRANKED": 0, "DUO_CARRY": 0, "spell21": 0, "SOLO": 0, "magicDamageDealt": 0, "kills": 0, "DUO": 0, "timestamp": 0, "MIDDLE": 0, "assists": 0, "spell4": 0, "spell6": 0, "spell7": 0, "SILVER": 0, "BRONZE": 0, "spell3": 0, "count": 0, "spell14": 0, "DIAMOND": 0, "spell12": 0, "spell13": 0, "spell11": 0, "pickRate": 0.0, "spell2": 0, "DUO_SUPPORT": 0}, "3001": {"GOLD": 0.0, "deaths": 8.0, "TOP": 0.0, "magicDamageDealtToChampions": 5028.0, "CHALLENGER": 0.0, "totalTimeCrowdControlDealt": 304.0, "PLATINUM": 0.0, "NONE": 0.0, "BOTTOM": 1.0, "winner": 1.0, "spell1": 0.0, "MASTER": 0.0, "JUNGLE": 0.0, "UNRANKED": 0.0, "DUO_CARRY": 1.0, "spell21": 0.5, "SOLO": 0.0, "magicDamageDealt": 51534.0, "kills": 20.0, "DUO": 0.0, "timestamp": 2137372.0, "MIDDLE": 0.0, "assists": 9.0, "spell4": 0.5, "spell6": 0.0, "spell7": 0.0, "SILVER": 0.0, "BRONZE": 1.0, "spell3": 0.0, "count": 1, "spell14": 0.0, "DIAMOND": 0.0, "spell12": 0.0, "spell13": 0.0, "spell11": 0.0, "pickRate": 0.006024096385542169, "spell2": 0.0, "DUO_SUPPORT": 0.0}, "3145": {"GOLD": 0.0, "deaths": 8.5, "TOP": 0.5, "magicDamageDealtToChampions": 2070.5, "CHALLENGER": 0.0, "totalTimeCrowdControlDealt": 79.5, "PLATINUM": 0.0, "NONE": 0.0, "BOTTOM": 0.5, "winner": 1.0, "spell1": 0.0, "MASTER": 0.0, "JUNGLE": 0.0, "UNRANKED": 1.0, "DUO_CARRY": 0.0, "spell21": 0.0, "SOLO": 0.0, "magicDamageDealt": 7715.5, "kills": 7.0, "DUO": 1.0, "timestamp": 1774007.5, "MIDDLE": 0.0, "assists": 9.5, "spell4": 0.25, "spell6": 0.0, "spell7": 0.25, "SILVER": 0.0, "BRONZE": 0.0, "spell3": 0.25, "count": 2, "spell14": 0.0, "DIAMOND": 0.0, "spell12": 0.25, "spell13": 0.0, "spell11": 0.0, "pickRate": 0.012048192771084338, "spell2": 0.0, "DUO_SUPPORT": 0.0}, "3003": {"GOLD": 0, "deaths": 0, "TOP": 0, "magicDamageDealtToChampions": 0, "CHALLENGER": 0, "totalTimeCrowdControlDealt": 0, "PLATINUM": 0, "NONE": 0, "BOTTOM": 0, "winner": 0, "spell1": 0, "MASTER": 0, "JUNGLE": 0, "UNRANKED": 0, "DUO_CARRY": 0, "spell21": 0, "SOLO": 0, "magicDamageDealt": 0, "kills": 0, "DUO": 0, "timestamp": 0, "MIDDLE": 0, "assists": 0, "spell4": 0, "spell6": 0, "spell7": 0, "SILVER": 0, "BRONZE": 0, "spell3": 0, "count": 0, "spell14": 0, "DIAMOND": 0, "spell12": 0, "spell13": 0, "spell11": 0, "pickRate": 0.0, "spell2": 0, "DUO_SUPPORT": 0}, "3041": {"GOLD": 0.0, "deaths": 10.666666666666666, "TOP": 0.0, "magicDamageDealtToChampions": 1495.3333333333333, "CHALLENGER": 0.0, "totalTimeCrowdControlDealt": 72.0, "PLATINUM": 0.3333333333333333, "NONE": 0.0, "BOTTOM": 1.0, "winner": 0.0, "spell1": 0.16666666666666666, "MASTER": 0.0, "JUNGLE": 0.0, "UNRANKED": 0.3333333333333333, "DUO_CARRY": 0.6666666666666666, "spell21": 0.16666666666666666, "SOLO": 0.0, "magicDamageDealt": 8780.666666666666, "kills": 1.3333333333333333, "DUO": 0.3333333333333333, "timestamp": 1183452.6666666667, "MIDDLE": 0.0, "assists": 4.0, "spell4": 0.3333333333333333, "spell6": 0.0, "spell7": 0.16666666666666666, "SILVER": 0.0, "BRONZE": 0.3333333333333333, "spell3": 0.0, "count": 3, "spell14": 0.0, "DIAMOND": 0.0, "spell12": 0.0, "spell13": 0.0, "spell11": 0.16666666666666666, "pickRate": 0.018072289156626505, "spell2": 0.0, "DUO_SUPPORT": 0.0}, "3165": {"GOLD": 0.0, "deaths": 11.5, "TOP": 0.0, "magicDamageDealtToChampions": 2099.0, "CHALLENGER": 0.0, "totalTimeCrowdControlDealt": 203.0, "PLATINUM": 1.0, "NONE": 0.0, "BOTTOM": 1.0, "winner": 0.5, "spell1": 0.0, "MASTER": 0.0, "JUNGLE": 0.0, "UNRANKED": 0.0, "DUO_CARRY": 1.0, "spell21": 0.0, "SOLO": 0.0, "magicDamageDealt": 15372.0, "kills": 13.0, "DUO": 0.0, "timestamp": 2192188.0, "MIDDLE": 0.0, "assists": 6.0, "spell4": 0.5, "spell6": 0.0, "spell7": 0.25, "SILVER": 0.0, "BRONZE": 0.0, "spell3": 0.0, "count": 2, "spell14": 0.25, "DIAMOND": 0.0, "spell12": 0.0, "spell13": 0.0, "spell11": 0.0, "pickRate": 0.012048192771084338, "spell2": 0.0, "DUO_SUPPORT": 0.0}, "1052": {"GOLD": 0.07142857142857142, "deaths": 6.785714285714286, "TOP": 0.07142857142857142, "magicDamageDealtToChampions": 2637.535714285714, "CHALLENGER": 0.0, "totalTimeCrowdControlDealt": 274.64285714285717, "PLATINUM": 0.03571428571428571, "NONE": 0.10714285714285714, "BOTTOM": 0.8571428571428571, "winner": 0.4642857142857143, "spell1": 0.017857142857142856, "MASTER": 0.0, "JUNGLE": 0.07142857142857142, "UNRANKED": 0.42857142857142855, "DUO_CARRY": 0.6071428571428571, "spell21": 0.03571428571428571, "SOLO": 0.14285714285714285, "magicDamageDealt": 15653.642857142857, "kills": 6.678571428571429, "DUO": 0.14285714285714285, "timestamp": 1189105.2857142857, "MIDDLE": 0.0, "assists": 6.035714285714286, "spell4": 0.44642857142857145, "spell6": 0.0, "spell7": 0.39285714285714285, "SILVER": 0.21428571428571427, "BRONZE": 0.17857142857142858, "spell3": 0.0, "count": 28, "spell14": 0.03571428571428571, "DIAMOND": 0.07142857142857142, "spell12": 0.03571428571428571, "spell13": 0.017857142857142856, "spell11": 0.017857142857142856, "pickRate": 0.1686746987951807, "spell2": 0.0, "DUO_SUPPORT": 0.0}, "3108": {"GOLD": 0.0, "deaths": 2.75, "TOP": 0.25, "magicDamageDealtToChampions": 6827.75, "CHALLENGER": 0.0, "totalTimeCrowdControlDealt": 358.75, "PLATINUM": 0.0, "NONE": 0.25, "BOTTOM": 0.5, "winner": 0.5, "spell1": 0.0, "MASTER": 0.0, "JUNGLE": 0.25, "UNRANKED": 0.0, "DUO_CARRY": 0.5, "spell21": 0.0, "SOLO": 0.25, "magicDamageDealt": 48721.5, "kills": 5.5, "DUO": 0.0, "timestamp": 1515191.25, "MIDDLE": 0.0, "assists": 6.25, "spell4": 0.5, "spell6": 0.0, "spell7": 0.5, "SILVER": 0.25, "BRONZE": 0.75, "spell3": 0.0, "count": 4, "spell14": 0.0, "DIAMOND": 0.0, "spell12": 0.0, "spell13": 0.0, "spell11": 0.0, "pickRate": 0.024096385542168676, "spell2": 0.0, "DUO_SUPPORT": 0.0}, "3504": {"GOLD": 0.0, "deaths": 12.0, "TOP": 0.0, "magicDamageDealtToChampions": 6250.0, "CHALLENGER": 0.0, "totalTimeCrowdControlDealt": 177.0, "PLATINUM": 0.0, "NONE": 0.0, "BOTTOM": 1.0, "winner": 1.0, "spell1": 0.0, "MASTER": 0.0, "JUNGLE": 0.0, "UNRANKED": 1.0, "DUO_CARRY": 0.0, "spell21": 0.0, "SOLO": 1.0, "magicDamageDealt": 33169.0, "kills": 18.0, "DUO": 0.0, "timestamp": 2076175.0, "MIDDLE": 0.0, "assists": 12.0, "spell4": 0.5, "spell6": 0.0, "spell7": 0.0, "SILVER": 0.0, "BRONZE": 0.0, "spell3": 0.0, "count": 1, "spell14": 0.5, "DIAMOND": 0.0, "spell12": 0.0, "spell13": 0.0, "spell11": 0.0, "pickRate": 0.006024096385542169, "spell2": 0.0, "DUO_SUPPORT": 0.0}, "1058": {"GOLD": 0.2, "deaths": 7.333333333333333, "TOP": 0.06666666666666667, "magicDamageDealtToChampions": 2690.133333333333, "CHALLENGER": 0.0, "totalTimeCrowdControlDealt": 132.53333333333333, "PLATINUM": 0.0, "NONE": 0.06666666666666667, "BOTTOM": 0.8666666666666667, "winner": 0.6666666666666666, "spell1": 0.03333333333333333, "MASTER": 0.0, "JUNGLE": 0.06666666666666667, "UNRANKED": 0.26666666666666666, "DUO_CARRY": 0.8, "spell21": 0.06666666666666667, "SOLO": 0.06666666666666667, "magicDamageDealt": 18585.8, "kills": 7.466666666666667, "DUO": 0.06666666666666667, "timestamp": 1458788.2666666666, "MIDDLE": 0.0, "assists": 7.933333333333334, "spell4": 0.4666666666666667, "spell6": 0.0, "spell7": 0.4, "SILVER": 0.2, "BRONZE": 0.3333333333333333, "spell3": 0.0, "count": 15, "spell14": 0.03333333333333333, "DIAMOND": 0.0, "spell12": 0.0, "spell13": 0.0, "spell11": 0.0, "pickRate": 0.09036144578313253, "spell2": 0.0, "DUO_SUPPORT": 0.0}, "3025": {"GOLD": 0.5, "deaths": 18.0, "TOP": 0.0, "magicDamageDealtToChampions": 4874.0, "CHALLENGER": 0.0, "totalTimeCrowdControlDealt": 216.5, "PLATINUM": 0.0, "NONE": 0.0, "BOTTOM": 1.0, "winner": 0.0, "spell1": 0.0, "MASTER": 0.0, "JUNGLE": 0.0, "UNRANKED": 0.5, "DUO_CARRY": 0.0, "spell21": 0.0, "SOLO": 0.0, "magicDamageDealt": 41410.0, "kills": 5.5, "DUO": 1.0, "timestamp": 2196765.0, "MIDDLE": 0.0, "assists": 16.5, "spell4": 0.25, "spell6": 0.0, "spell7": 0.5, "SILVER": 0.0, "BRONZE": 0.0, "spell3": 0.0, "count": 2, "spell14": 0.0, "DIAMOND": 0.0, "spell12": 0.0, "spell13": 0.25, "spell11": 0.0, "pickRate": 0.012048192771084338, "spell2": 0.0, "DUO_SUPPORT": 0.0}, "3100": {"GOLD": 0.0, "deaths": 4.0, "TOP": 0.0, "magicDamageDealtToChampions": 18817.0, "CHALLENGER": 0.0, "totalTimeCrowdControlDealt": 217.0, "PLATINUM": 0.0, "NONE": 0.0, "BOTTOM": 1.0, "winner": 0.0, "spell1": 0.0, "MASTER": 0.0, "JUNGLE": 0.0, "UNRANKED": 0.0, "DUO_CARRY": 1.0, "spell21": 0.0, "SOLO": 0.0, "magicDamageDealt": 141567.0, "kills": 10.0, "DUO": 0.0, "timestamp": 1618685.0, "MIDDLE": 0.0, "assists": 14.0, "spell4": 0.5, "spell6": 0.0, "spell7": 0.5, "SILVER": 0.0, "BRONZE": 1.0, "spell3": 0.0, "count": 1, "spell14": 0.0, "DIAMOND": 0.0, "spell12": 0.0, "spell13": 0.0, "spell11": 0.0, "pickRate": 0.006024096385542169, "spell2": 0.0, "DUO_SUPPORT": 0.0}, "3124": {"GOLD": 0.0, "deaths": 11.0, "TOP": 0.0, "magicDamageDealtToChampions": 5585.0, "CHALLENGER": 0.0, "totalTimeCrowdControlDealt": 261.0, "PLATINUM": 1.0, "NONE": 0.0, "BOTTOM": 1.0, "winner": 1.0, "spell1": 0.0, "MASTER": 0.0, "JUNGLE": 0.0, "UNRANKED": 0.0, "DUO_CARRY": 0.0, "spell21": 0.0, "SOLO": 0.0, "magicDamageDealt": 27074.0, "kills": 14.0, "DUO": 1.0, "timestamp": 1989419.0, "MIDDLE": 0.0, "assists": 18.0, "spell4": 0.5, "spell6": 0.0, "spell7": 0.5, "SILVER": 0.0, "BRONZE": 0.0, "spell3": 0.0, "count": 1, "spell14": 0.0, "DIAMOND": 0.0, "spell12": 0.0, "spell13": 0.0, "spell11": 0.0, "pickRate": 0.006024096385542169, "spell2": 0.0, "DUO_SUPPORT": 0.0}, "3089": {"GOLD": 0.0, "deaths": 10.375, "TOP": 0.0, "magicDamageDealtToChampions": 2500.0, "CHALLENGER": 0.0, "totalTimeCrowdControlDealt": 210.5, "PLATINUM": 0.25, "NONE": 0.0, "BOTTOM": 1.0, "winner": 0.5, "spell1": 0.0, "MASTER": 0.0, "JUNGLE": 0.0, "UNRANKED": 0.125, "DUO_CARRY": 1.0, "spell21": 0.0625, "SOLO": 0.0, "magicDamageDealt": 15437.5, "kills": 12.0, "DUO": 0.0, "timestamp": 2281855.375, "MIDDLE": 0.0, "assists": 9.25, "spell4": 0.5, "spell6": 0.0, "spell7": 0.4375, "SILVER": 0.25, "BRONZE": 0.375, "spell3": 0.0, "count": 8, "spell14": 0.0, "DIAMOND": 0.0, "spell12": 0.0, "spell13": 0.0, "spell11": 0.0, "pickRate": 0.04819277108433735, "spell2": 0.0, "DUO_SUPPORT": 0.0}, "3135": {"GOLD": 0, "deaths": 0, "TOP": 0, "magicDamageDealtToChampions": 0, "CHALLENGER": 0, "totalTimeCrowdControlDealt": 0, "PLATINUM": 0, "NONE": 0, "BOTTOM": 0, "winner": 0, "spell1": 0, "MASTER": 0, "JUNGLE": 0, "UNRANKED": 0, "DUO_CARRY": 0, "spell21": 0, "SOLO": 0, "magicDamageDealt": 0, "kills": 0, "DUO": 0, "timestamp": 0, "MIDDLE": 0, "assists": 0, "spell4": 0, "spell6": 0, "spell7": 0, "SILVER": 0, "BRONZE": 0, "spell3": 0, "count": 0, "spell14": 0, "DIAMOND": 0, "spell12": 0, "spell13": 0, "spell11": 0, "pickRate": 0.0, "spell2": 0, "DUO_SUPPORT": 0}, "3152": {"GOLD": 0, "deaths": 0, "TOP": 0, "magicDamageDealtToChampions": 0, "CHALLENGER": 0, "totalTimeCrowdControlDealt": 0, "PLATINUM": 0, "NONE": 0, "BOTTOM": 0, "winner": 0, "spell1": 0, "MASTER": 0, "JUNGLE": 0, "UNRANKED": 0, "DUO_CARRY": 0, "spell21": 0, "SOLO": 0, "magicDamageDealt": 0, "kills": 0, "DUO": 0, "timestamp": 0, "MIDDLE": 0, "assists": 0, "spell4": 0, "spell6": 0, "spell7": 0, "SILVER": 0, "BRONZE": 0, "spell3": 0, "count": 0, "spell14": 0, "DIAMOND": 0, "spell12": 0, "spell13": 0, "spell11": 0, "pickRate": 0.0, "spell2": 0, "DUO_SUPPORT": 0}, "3151": {"GOLD": 0.0, "deaths": 2.0, "TOP": 0.0, "magicDamageDealtToChampions": 3368.0, "CHALLENGER": 0.0, "totalTimeCrowdControlDealt": 48.0, "PLATINUM": 0.0, "NONE": 0.0, "BOTTOM": 1.0, "winner": 1.0, "spell1": 0.0, "MASTER": 0.0, "JUNGLE": 0.0, "UNRANKED": 0.0, "DUO_CARRY": 1.0, "spell21": 0.0, "SOLO": 0.0, "magicDamageDealt": 21999.0, "kills": 0.0, "DUO": 0.0, "timestamp": 867728.0, "MIDDLE": 0.0, "assists": 3.0, "spell4": 0.5, "spell6": 0.0, "spell7": 0.0, "SILVER": 1.0, "BRONZE": 0.0, "spell3": 0.0, "count": 1, "spell14": 0.5, "DIAMOND": 0.0, "spell12": 0.0, "spell13": 0.0, "spell11": 0.0, "pickRate": 0.006024096385542169, "spell2": 0.0, "DUO_SUPPORT": 0.0}, "3136": {"GOLD": 0.0, "deaths": 2.0, "TOP": 0.0, "magicDamageDealtToChampions": 3368.0, "CHALLENGER": 0.0, "totalTimeCrowdControlDealt": 48.0, "PLATINUM": 0.0, "NONE": 0.0, "BOTTOM": 1.0, "winner": 1.0, "spell1": 0.0, "MASTER": 0.0, "JUNGLE": 0.0, "UNRANKED": 0.0, "DUO_CARRY": 1.0, "spell21": 0.0, "SOLO": 0.0, "magicDamageDealt": 21999.0, "kills": 0.0, "DUO": 0.0, "timestamp": 700375.0, "MIDDLE": 0.0, "assists": 3.0, "spell4": 0.5, "spell6": 0.0, "spell7": 0.0, "SILVER": 1.0, "BRONZE": 0.0, "spell3": 0.0, "count": 1, "spell14": 0.5, "DIAMOND": 0.0, "spell12": 0.0, "spell13": 0.0, "spell11": 0.0, "pickRate": 0.006024096385542169, "spell2": 0.0, "DUO_SUPPORT": 0.0}, "3157": {"GOLD": 0.17647058823529413, "deaths": 9.705882352941176, "TOP": 0.0, "magicDamageDealtToChampions": 3237.470588235294, "CHALLENGER": 0.0, "totalTimeCrowdControlDealt": 172.2941176470588, "PLATINUM": 0.17647058823529413, "NONE": 0.11764705882352941, "BOTTOM": 0.9411764705882353, "winner": 0.35294117647058826, "spell1": 0.0, "MASTER": 0.0, "JUNGLE": 0.058823529411764705, "UNRANKED": 0.23529411764705882, "DUO_CARRY": 0.8823529411764706, "spell21": 0.0, "SOLO": 0.0, "magicDamageDealt": 21471.0, "kills": 8.117647058823529, "DUO": 0.0, "timestamp": 1989317.5882352942, "MIDDLE": 0.0, "assists": 8.588235294117647, "spell4": 0.5, "spell6": 0.0, "spell7": 0.47058823529411764, "SILVER": 0.11764705882352941, "BRONZE": 0.29411764705882354, "spell3": 0.0, "count": 17, "spell14": 0.0, "DIAMOND": 0.0, "spell12": 0.0, "spell13": 0.0, "spell11": 0.0, "pickRate": 0.10240963855421686, "spell2": 0.029411764705882353, "DUO_SUPPORT": 0.0}, "3078": {"GOLD": 0.24468085106382978, "deaths": 8.106382978723405, "TOP": 0.031914893617021274, "magicDamageDealtToChampions": 2387.1702127659573, "CHALLENGER": 0.0, "totalTimeCrowdControlDealt": 325.2659574468085, "PLATINUM": 0.0851063829787234, "NONE": 0.010638297872340425, "BOTTOM": 0.9361702127659575, "winner": 0.6595744680851063, "spell1": 0.005319148936170213, "MASTER": 0.0, "JUNGLE": 0.010638297872340425, "UNRANKED": 0.22340425531914893, "DUO_CARRY": 0.8191489361702128, "spell21": 0.03723404255319149, "SOLO": 0.0425531914893617, "magicDamageDealt": 14264.436170212766, "kills": 14.797872340425531, "DUO": 0.1276595744680851, "timestamp": 2114745.4574468085, "MIDDLE": 0.02127659574468085, "assists": 11.117021276595745, "spell4": 0.4734042553191489, "spell6": 0.0, "spell7": 0.4095744680851064, "SILVER": 0.30851063829787234, "BRONZE": 0.13829787234042554, "spell3": 0.005319148936170213, "count": 94, "spell14": 0.02127659574468085, "DIAMOND": 0.0, "spell12": 0.0425531914893617, "spell13": 0.005319148936170213, "spell11": 0.0, "pickRate": 0.5662650602409639, "spell2": 0.0, "DUO_SUPPORT": 0.0}, "3057": {"GOLD": 0.20512820512820512, "deaths": 7.615384615384615, "TOP": 0.05128205128205128, "magicDamageDealtToChampions": 2653.769230769231, "CHALLENGER": 0.0, "totalTimeCrowdControlDealt": 293.2564102564103, "PLATINUM": 0.0, "NONE": 0.0, "BOTTOM": 0.9230769230769231, "winner": 0.6153846153846154, "spell1": 0.01282051282051282, "MASTER": 0.0, "JUNGLE": 0.0, "UNRANKED": 0.28205128205128205, "DUO_CARRY": 0.7435897435897436, "spell21": 0.02564102564102564, "SOLO": 0.05128205128205128, "magicDamageDealt": 14741.28205128205, "kills": 13.58974358974359, "DUO": 0.20512820512820512, "timestamp": 1630250.8205128205, "MIDDLE": 0.02564102564102564, "assists": 10.948717948717949, "spell4": 0.46153846153846156, "spell6": 0.0, "spell7": 0.4230769230769231, "SILVER": 0.358974358974359, "BRONZE": 0.1282051282051282, "spell3": 0.0, "count": 39, "spell14": 0.02564102564102564, "DIAMOND": 0.02564102564102564, "spell12": 0.05128205128205128, "spell13": 0.0, "spell11": 0.0, "pickRate": 0.23493975903614459, "spell2": 0.0, "DUO_SUPPORT": 0.0}, "3285": {"GOLD": 0.0, "deaths": 7.7, "TOP": 0.1, "magicDamageDealtToChampions": 3985.8, "CHALLENGER": 0.0, "totalTimeCrowdControlDealt": 113.0, "PLATINUM": 0.1, "NONE": 0.0, "BOTTOM": 0.9, "winner": 0.4, "spell1": 0.0, "MASTER": 0.0, "JUNGLE": 0.0, "UNRANKED": 0.1, "DUO_CARRY": 0.9, "spell21": 0.05, "SOLO": 0.1, "magicDamageDealt": 29635.4, "kills": 7.1, "DUO": 0.0, "timestamp": 1736382.1, "MIDDLE": 0.0, "assists": 6.8, "spell4": 0.5, "spell6": 0.0, "spell7": 0.4, "SILVER": 0.1, "BRONZE": 0.6, "spell3": 0.0, "count": 10, "spell14": 0.05, "DIAMOND": 0.1, "spell12": 0.0, "spell13": 0.0, "spell11": 0.0, "pickRate": 0.060240963855421686, "spell2": 0.0, "DUO_SUPPORT": 0.0}, "3174": {"GOLD": 0.0, "deaths": 4.0, "TOP": 0.0, "magicDamageDealtToChampions": 18817.0, "CHALLENGER": 0.0, "totalTimeCrowdControlDealt": 217.0, "PLATINUM": 0.0, "NONE": 0.0, "BOTTOM": 1.0, "winner": 0.0, "spell1": 0.0, "MASTER": 0.0, "JUNGLE": 0.0, "UNRANKED": 0.0, "DUO_CARRY": 1.0, "spell21": 0.0, "SOLO": 0.0, "magicDamageDealt": 141567.0, "kills": 10.0, "DUO": 0.0, "timestamp": 659331.0, "MIDDLE": 0.0, "assists": 14.0, "spell4": 0.5, "spell6": 0.0, "spell7": 0.5, "SILVER": 0.0, "BRONZE": 1.0, "spell3": 0.0, "count": 1, "spell14": 0.0, "DIAMOND": 0.0, "spell12": 0.0, "spell13": 0.0, "spell11": 0.0, "pickRate": 0.006024096385542169, "spell2": 0.0, "DUO_SUPPORT": 0.0}, "1026": {"GOLD": 0.08333333333333333, "deaths": 10.083333333333334, "TOP": 0.08333333333333333, "magicDamageDealtToChampions": 2245.0833333333335, "CHALLENGER": 0.0, "totalTimeCrowdControlDealt": 118.58333333333333, "PLATINUM": 0.08333333333333333, "NONE": 0.08333333333333333, "BOTTOM": 0.75, "winner": 0.3333333333333333, "spell1": 0.0, "MASTER": 0.0, "JUNGLE": 0.08333333333333333, "UNRANKED": 0.6666666666666666, "DUO_CARRY": 0.5833333333333334, "spell21": 0.041666666666666664, "SOLO": 0.0, "magicDamageDealt": 19674.333333333332, "kills": 5.5, "DUO": 0.3333333333333333, "timestamp": 1597827.4166666667, "MIDDLE": 0.08333333333333333, "assists": 5.083333333333333, "spell4": 0.4166666666666667, "spell6": 0.041666666666666664, "spell7": 0.375, "SILVER": 0.08333333333333333, "BRONZE": 0.08333333333333333, "spell3": 0.041666666666666664, "count": 12, "spell14": 0.041666666666666664, "DIAMOND": 0.0, "spell12": 0.041666666666666664, "spell13": 0.0, "spell11": 0.0, "pickRate": 0.07228915662650602, "spell2": 0.0, "DUO_SUPPORT": 0.0}, "3116": {"GOLD": 0.0, "deaths": 6.0, "TOP": 0.0, "magicDamageDealtToChampions": 5053.0, "CHALLENGER": 0.0, "totalTimeCrowdControlDealt": 312.0, "PLATINUM": 0.0, "NONE": 0.0, "BOTTOM": 0.0, "winner": 0.0, "spell1": 0.0, "MASTER": 0.0, "JUNGLE": 0.0, "UNRANKED": 1.0, "DUO_CARRY": 1.0, "spell21": 0.0, "SOLO": 0.0, "magicDamageDealt": 104174.0, "kills": 2.0, "DUO": 0.0, "timestamp": 2522987.0, "MIDDLE": 1.0, "assists": 4.0, "spell4": 0.0, "spell6": 0.5, "spell7": 0.5, "SILVER": 0.0, "BRONZE": 0.0, "spell3": 0.0, "count": 1, "spell14": 0.0, "DIAMOND": 0.0, "spell12": 0.0, "spell13": 0.0, "spell11": 0.0, "pickRate": 0.006024096385542169, "spell2": 0.0, "DUO_SUPPORT": 0.0}, "3115": {"GOLD": 0.0, "deaths": 3.0, "TOP": 0.25, "magicDamageDealtToChampions": 8843.25, "CHALLENGER": 0.0, "totalTimeCrowdControlDealt": 449.25, "PLATINUM": 0.0, "NONE": 0.0, "BOTTOM": 0.75, "winner": 0.5, "spell1": 0.0, "MASTER": 0.0, "JUNGLE": 0.0, "UNRANKED": 0.0, "DUO_CARRY": 0.75, "spell21": 0.0, "SOLO": 0.25, "magicDamageDealt": 58888.0, "kills": 7.75, "DUO": 0.0, "timestamp": 2253508.25, "MIDDLE": 0.0, "assists": 8.75, "spell4": 0.5, "spell6": 0.0, "spell7": 0.5, "SILVER": 0.25, "BRONZE": 0.75, "spell3": 0.0, "count": 4, "spell14": 0.0, "DIAMOND": 0.0, "spell12": 0.0, "spell13": 0.0, "spell11": 0.0, "pickRate": 0.024096385542168676, "spell2": 0.0, "DUO_SUPPORT": 0.0}, "3113": {"GOLD": 0.16666666666666666, "deaths": 9.833333333333334, "TOP": 0.0, "magicDamageDealtToChampions": 5480.833333333333, "CHALLENGER": 0.0, "totalTimeCrowdControlDealt": 147.0, "PLATINUM": 0.0, "NONE": 0.0, "BOTTOM": 1.0, "winner": 0.3333333333333333, "spell1": 0.0, "MASTER": 0.0, "JUNGLE": 0.0, "UNRANKED": 0.16666666666666666, "DUO_CARRY": 0.8333333333333334, "spell21": 0.08333333333333333, "SOLO": 0.16666666666666666, "magicDamageDealt": 38991.333333333336, "kills": 8.0, "DUO": 0.0, "timestamp": 1552305.0, "MIDDLE": 0.0, "assists": 8.333333333333334, "spell4": 0.5, "spell6": 0.0, "spell7": 0.3333333333333333, "SILVER": 0.0, "BRONZE": 0.5, "spell3": 0.0, "count": 6, "spell14": 0.08333333333333333, "DIAMOND": 0.16666666666666666, "spell12": 0.0, "spell13": 0.0, "spell11": 0.0, "pickRate": 0.03614457831325301, "spell2": 0.0, "DUO_SUPPORT": 0.0}, "summary": {"GOLD": 0.19879518072289157, "deaths": 8.391566265060241, "TOP": 0.03614457831325301, "magicDamageDealtToChampions": 2441.8253012048194, "CHALLENGER": 0.0, "totalTimeCrowdControlDealt": 272.71084337349396, "PLATINUM": 0.09036144578313253, "NONE": 0.024096385542168676, "BOTTOM": 0.927710843373494, "winner": 0.5481927710843374, "spell1": 0.009036144578313253, "MASTER": 0.0, "JUNGLE": 0.018072289156626505, "UNRANKED": 0.26506024096385544, "DUO_CARRY": 0.7831325301204819, "spell21": 0.03614457831325301, "SOLO": 0.04819277108433735, "magicDamageDealt": 15188.77108433735, "kills": 11.674698795180722, "DUO": 0.14457831325301204, "MIDDLE": 0.018072289156626505, "assists": 9.680722891566266, "spell4": 0.463855421686747, "spell6": 0.0030120481927710845, "spell7": 0.40963855421686746, "SILVER": 0.25903614457831325, "BRONZE": 0.16265060240963855, "spell3": 0.009036144578313253, "count": 166, "spell14": 0.024096385542168676, "DIAMOND": 0.024096385542168676, "spell12": 0.030120481927710843, "spell13": 0.009036144578313253, "spell11": 0.0030120481927710845, "pickRate": 0.00020569069323959124, "spell2": 0.0030120481927710845, "DUO_SUPPORT": 0.0}, "3027": {"GOLD": 0, "deaths": 0, "TOP": 0, "magicDamageDealtToChampions": 0, "CHALLENGER": 0, "totalTimeCrowdControlDealt": 0, "PLATINUM": 0, "NONE": 0, "BOTTOM": 0, "winner": 0, "spell1": 0, "MASTER": 0, "JUNGLE": 0, "UNRANKED": 0, "DUO_CARRY": 0, "spell21": 0, "SOLO": 0, "magicDamageDealt": 0, "kills": 0, "DUO": 0, "timestamp": 0, "MIDDLE": 0, "assists": 0, "spell4": 0, "spell6": 0, "spell7": 0, "SILVER": 0, "BRONZE": 0, "spell3": 0, "count": 0, "spell14": 0, "DIAMOND": 0, "spell12": 0, "spell13": 0, "spell11": 0, "pickRate": 0.0, "spell2": 0, "DUO_SUPPORT": 0}, "3191": {"GOLD": 0.2, "deaths": 8.2, "TOP": 0.0, "magicDamageDealtToChampions": 3845.2, "CHALLENGER": 0.0, "totalTimeCrowdControlDealt": 224.2, "PLATINUM": 0.1, "NONE": 0.1, "BOTTOM": 1.0, "winner": 0.4, "spell1": 0.0, "MASTER": 0.0, "JUNGLE": 0.0, "UNRANKED": 0.3, "DUO_CARRY": 0.9, "spell21": 0.05, "SOLO": 0.0, "magicDamageDealt": 27336.2, "kills": 12.5, "DUO": 0.0, "timestamp": 2031202.3, "MIDDLE": 0.0, "assists": 11.2, "spell4": 0.5, "spell6": 0.0, "spell7": 0.4, "SILVER": 0.0, "BRONZE": 0.4, "spell3": 0.0, "count": 10, "spell14": 0.0, "DIAMOND": 0.0, "spell12": 0.0, "spell13": 0.0, "spell11": 0.0, "pickRate": 0.060240963855421686, "spell2": 0.05, "DUO_SUPPORT": 0.0}}